{
  "generated": "2026-07-09T13:41:23.749639Z",
  "source_file": "20260708c.txt",
  "count": 36,
  "filings": [
    {
      "doc_number": "L26000354270",
      "name": "MASON RANCH, LLC",
      "entity_type": "Florida LLC",
      "filing_date": "2026-06-30",
      "city": "Odessa",
      "county": "PASCO",
      "address": "18419 Tyler Rd",
      "registered_agent": "Mason               Michael       E",
      "owner": ""
    },
    {
      "doc_number": "L26000354590",
      "name": "Y&R FLASH LLC",
      "entity_type": "Florida LLC",
      "filing_date": "2026-06-30",
      "city": "New Port Richey",
      "county": "PASCO",
      "address": "6804 Greenwich Ave",
      "registered_agent": "Rivero Milanes      Yarien        J",
      "owner": ""
    },
    {
      "doc_number": "L26000354630",
      "name": "MAMIHAMMER STUDIO LLC",
      "entity_type": "Florida LLC",
      "filing_date": "2026-06-01",
      "city": "Lutz",
      "county": "PASCO",
      "address": "5014 Torrey Hills Lane",
      "registered_agent": "Pacheco             Sergio",
      "owner": ""
    },
    {
      "doc_number": "L26000354381",
      "name": "DWSS LLC",
      "entity_type": "Florida LLC",
      "filing_date": "2026-08-01",
      "city": "Zephyrhills",
      "county": "PASCO",
      "address": "38141 Palm Grove Drive",
      "registered_agent": "Messer              Wendy         S",
      "owner": ""
    },
    {
      "doc_number": "L26000354551",
      "name": "G-RECON LLC",
      "entity_type": "Florida LLC",
      "filing_date": "2026-07-04",
      "city": "Trinity",
      "county": "PASCO",
      "address": "1248 Ketzal Dr",
      "registered_agent": "Grecco              Nicholas      A",
      "owner": ""
    },
    {
      "doc_number": "L26000354831",
      "name": "BODY CONTOUR & WELLNESS SPA LLC",
      "entity_type": "Florida LLC",
      "filing_date": "2026-07-01",
      "city": "Wesley Chapel",
      "county": "PASCO",
      "address": "2649 Windguard Circle",
      "registered_agent": "Angers Nash         Alexandre",
      "owner": ""
    },
    {
      "doc_number": "L26000354841",
      "name": "KARLUXE CLEANING, LLC",
      "entity_type": "Florida LLC",
      "filing_date": "2026-06-30",
      "city": "Wesley Chapel",
      "county": "PASCO",
      "address": "7769 Tranquility Lp #305",
      "registered_agent": "Inc Authority Ra",
      "owner": ""
    },
    {
      "doc_number": "L26000355001",
      "name": "KRISHNA TRADING LLC",
      "entity_type": "Florida LLC",
      "filing_date": "2026-06-30",
      "city": "Zephyrhills",
      "county": "PASCO",
      "address": "36750 Eiland Blvd",
      "registered_agent": "Patel               Akash",
      "owner": ""
    },
    {
      "doc_number": "L26000355441",
      "name": "DUOTAP LLC",
      "entity_type": "Florida LLC",
      "filing_date": "2026-06-30",
      "city": "Land O Lakes",
      "county": "PASCO",
      "address": "19520 Hayden Lake Court",
      "registered_agent": "Wright              Marissa       D",
      "owner": ""
    },
    {
      "doc_number": "L26000355571",
      "name": "EILEENS BOUTIQUE LLC",
      "entity_type": "Florida LLC",
      "filing_date": "2026-07-18",
      "city": "New Port Richey",
      "county": "PASCO",
      "address": "2331 Woodbend Circle",
      "registered_agent": "Valentin            Barbara       E",
      "owner": ""
    },
    {
      "doc_number": "L26000355591",
      "name": "BLUEWATER HEALTH GROUP LLC",
      "entity_type": "Florida LLC",
      "filing_date": "2026-07-01",
      "city": "New Port Richey",
      "county": "PASCO",
      "address": "9332 State Road 54",
      "registered_agent": "Patel               Sahil         Pmd",
      "owner": ""
    },
    {
      "doc_number": "L26000354832",
      "name": "INSPIRED LIVING SERVICES LLC",
      "entity_type": "Florida LLC",
      "filing_date": "2026-07-01",
      "city": "Wesley Chapel",
      "county": "PASCO",
      "address": "28400 Alder Ave",
      "registered_agent": "Hawkins             Monique       A",
      "owner": ""
    },
    {
      "doc_number": "L26000354233",
      "name": "KAREN'S MANUFACTURED MOBILE HOME SALES LLC",
      "entity_type": "Florida LLC",
      "filing_date": "2026-06-30",
      "city": "Zephyrhills",
      "county": "PASCO",
      "address": "7025 Fort King Road",
      "registered_agent": "Mowrey              Karen         M",
      "owner": ""
    },
    {
      "doc_number": "L26000355263",
      "name": "BLACK DOG ENVIRONMENTAL LLC",
      "entity_type": "Florida LLC",
      "filing_date": "2026-07-01",
      "city": "Zephyrhills",
      "county": "PASCO",
      "address": "5153 16Th St",
      "registered_agent": "Sommers             Theresa",
      "owner": ""
    },
    {
      "doc_number": "L26000354754",
      "name": "MPG LOGISTICS GROUP LLC",
      "entity_type": "Florida LLC",
      "filing_date": "2026-06-30",
      "city": "Trinity",
      "county": "PASCO",
      "address": "11813 Trevally Loop",
      "registered_agent": "Gonzalez            Marc          S",
      "owner": ""
    },
    {
      "doc_number": "L26000354864",
      "name": "SLINGIN' SEED, LLC",
      "entity_type": "Florida LLC",
      "filing_date": "2026-06-30",
      "city": "Dade City",
      "county": "PASCO",
      "address": "38109 Pasco Avenue",
      "registered_agent": "R. Seth Mann, P.A.",
      "owner": ""
    },
    {
      "doc_number": "L26000354005",
      "name": "SOURCING SWEET HOME BAKES LLC",
      "entity_type": "Florida LLC",
      "filing_date": "2026-06-30",
      "city": "New Port Richey",
      "county": "PASCO",
      "address": "7407 Humboldt Avenue",
      "registered_agent": "Rivera Salgado      Janice",
      "owner": ""
    },
    {
      "doc_number": "L26000354105",
      "name": "BAUSY LLC",
      "entity_type": "Florida LLC",
      "filing_date": "2026-06-30",
      "city": "Odessa",
      "county": "PASCO",
      "address": "16957 Silver Shores Ln",
      "registered_agent": "Bauserman           Gregg         A",
      "owner": ""
    },
    {
      "doc_number": "L26000354255",
      "name": "XELOR LABS LLC",
      "entity_type": "Florida LLC",
      "filing_date": "2026-06-30",
      "city": "Odessa",
      "county": "PASCO",
      "address": "16957 Silver Shores Ln",
      "registered_agent": "Bauserman           Gregg         A",
      "owner": ""
    },
    {
      "doc_number": "L26000355345",
      "name": "KACHELLE BOUTIQUE LLC",
      "entity_type": "Florida LLC",
      "filing_date": "2026-06-30",
      "city": "Wesley Chapel",
      "county": "PASCO",
      "address": "34065 Soaring Bamboo Path",
      "registered_agent": "Northwest Registered Agent Llc",
      "owner": ""
    },
    {
      "doc_number": "L26000354026",
      "name": "GULFSIDE COATING LLC",
      "entity_type": "Florida LLC",
      "filing_date": "2026-06-30",
      "city": "Holiday",
      "county": "PASCO",
      "address": "4946 Gaslight Ave.",
      "registered_agent": "Horn                Matthew       P",
      "owner": ""
    },
    {
      "doc_number": "L26000354616",
      "name": "ANGEL WINGS KITCHEN LLC",
      "entity_type": "Florida LLC",
      "filing_date": "2026-06-25",
      "city": "Holiday",
      "county": "PASCO",
      "address": "5221 Hawk Dr",
      "registered_agent": "Kret                Janusz",
      "owner": ""
    },
    {
      "doc_number": "L26000354766",
      "name": "VETERAN HARBOR HOUSE, LLC",
      "entity_type": "Florida LLC",
      "filing_date": "2026-06-30",
      "city": "Lutz",
      "county": "PASCO",
      "address": "18489 N Us Hwy 41 St 2427",
      "registered_agent": "Inc Authority Ra",
      "owner": ""
    },
    {
      "doc_number": "L26000355186",
      "name": "MFT LOGISTICS LLC",
      "entity_type": "Florida LLC",
      "filing_date": "2026-06-30",
      "city": "San Antonio",
      "county": "PASCO",
      "address": "31834 Griffin Sands Lane",
      "registered_agent": "Northwest Registered Agent Llc",
      "owner": ""
    },
    {
      "doc_number": "M26000010626",
      "name": "ON SPOT MANAGEMENT, LLC",
      "entity_type": "Foreign LLC",
      "filing_date": "2026-07-07",
      "city": "San Antonio",
      "county": "PASCO",
      "address": "1635 Ne Loop 410 Ste 700",
      "registered_agent": "C T Corporation System",
      "owner": ""
    },
    {
      "doc_number": "L26000354087",
      "name": "SUNLIGHT HOLDINGS LLC",
      "entity_type": "Florida LLC",
      "filing_date": "2026-06-30",
      "city": "Wesley Chapel",
      "county": "PASCO",
      "address": "32643 Thorncastle Dr",
      "registered_agent": "Desir               Nathalie",
      "owner": ""
    },
    {
      "doc_number": "L26000354297",
      "name": "XELOR COIN LLC",
      "entity_type": "Florida LLC",
      "filing_date": "2026-06-30",
      "city": "Odessa",
      "county": "PASCO",
      "address": "16957 Silver Shores Ln",
      "registered_agent": "Bauserman           Gregg         A",
      "owner": ""
    },
    {
      "doc_number": "P26000034197",
      "name": "NATURE CONNECTIONS, INC.",
      "entity_type": "FL Corporation",
      "filing_date": "2026-06-30",
      "city": "New Port Richey",
      "county": "PASCO",
      "address": "10875 Littleton Isle Dr",
      "registered_agent": "Yates               Nicole        M",
      "owner": ""
    },
    {
      "doc_number": "L26000354587",
      "name": "SUGAR GHOUL LLC",
      "entity_type": "Florida LLC",
      "filing_date": "2026-06-29",
      "city": "Lutz",
      "county": "PASCO",
      "address": "25910 Sierra Center Blvd",
      "registered_agent": "Lacy Pennell",
      "owner": ""
    },
    {
      "doc_number": "L26000354657",
      "name": "LEZAMA HOLDINGS LLC",
      "entity_type": "Florida LLC",
      "filing_date": "2026-06-26",
      "city": "Odessa",
      "county": "PASCO",
      "address": "7015 Longfellow Ranch Rd",
      "registered_agent": "Rahman              Javed         Sesq.",
      "owner": ""
    },
    {
      "doc_number": "L26000354228",
      "name": "SAWYER FACILITIES GROUP LLC",
      "entity_type": "Florida LLC",
      "filing_date": "2026-06-30",
      "city": "Dade City",
      "county": "PASCO",
      "address": "14045 21St St",
      "registered_agent": "Johnson             Darryl        J",
      "owner": ""
    },
    {
      "doc_number": "L26000354358",
      "name": "TITA LORI'S CLASSIC FILIPINO BREAD & TREATS LLC",
      "entity_type": "Florida LLC",
      "filing_date": "2026-06-30",
      "city": "Port Richey",
      "county": "PASCO",
      "address": "7520 Oakshire Dr",
      "registered_agent": "Villalpando         Lorivel       C",
      "owner": ""
    },
    {
      "doc_number": "L26000354428",
      "name": "DAWG TIRED LLC",
      "entity_type": "Florida LLC",
      "filing_date": "2026-07-07",
      "city": "Lutz",
      "county": "PASCO",
      "address": "1796 Parterre Ave",
      "registered_agent": "Registered Agents Inc",
      "owner": ""
    },
    {
      "doc_number": "L26000354239",
      "name": "DEFENDER EMERGENCY MANAGEMENT, LLC",
      "entity_type": "Florida LLC",
      "filing_date": "2026-06-25",
      "city": "Wesley Chapel",
      "county": "PASCO",
      "address": "1150 Helmsdale Dr",
      "registered_agent": "Colella             John          R",
      "owner": ""
    },
    {
      "doc_number": "L26000354369",
      "name": "BAUSERMAN CONSULTATION GROUP LLC",
      "entity_type": "Florida LLC",
      "filing_date": "2026-06-30",
      "city": "Odessa",
      "county": "PASCO",
      "address": "16957 Silver Shores Ln",
      "registered_agent": "Bauserman           Gregg         A",
      "owner": ""
    },
    {
      "doc_number": "L26000354829",
      "name": "SOFT RADIANCE WALL ART LLC",
      "entity_type": "Florida LLC",
      "filing_date": "2026-06-30",
      "city": "Wesley Chapel",
      "county": "PASCO",
      "address": "29800 Birds Eye Dr",
      "registered_agent": "Soper               Marina",
      "owner": ""
    }
  ]
}